{
  "batchid": 3116,
  "topicid": 31891,
  "classes_total": 6,
  "classes": [
    {
      "title": "Physics | L-02 | Center of Mass | PMP Sir",
      "id": "4512557",
      "date": "05-Aug-2025 08:30",
      "video_url": "4512557_0_6099805894914367"
    },
    {
      "title": "Organic Chem | L-12 | GOC-1 | DN Sir",
      "id": "4511937",
      "date": "04-Aug-2025 12:00",
      "video_url": "4511937_0_8475332992085897"
    },
    {
      "title": "Botany | L-01 | Sexual Reproduction in Flowering Plants | Dr.DA Sir",
      "id": "4511787",
      "date": "04-Aug-2025 10:15",
      "video_url": "4511787_0_6325510745319911"
    },
    {
      "title": "Physics | L-01 | Center of Mass | PMP Sir",
      "id": "4511650",
      "date": "04-Aug-2025 08:30",
      "video_url": "4511650_0_8322304633058973"
    },
    {
      "title": "Organic Chem | L-11 | GOC-1 | DN Sir",
      "id": "4510820",
      "date": "02-Aug-2025 08:55",
      "video_url": "4510820_0_9802726828526665"
    },
    {
      "title": "Physics | L-09 | Work Power Energy | PMP Sir",
      "id": "4510713",
      "date": "02-Aug-2025 06:45",
      "video_url": "4510713_0_3749030874323645"
    }
  ],
  "notes_total": 0,
  "notes": []
}