{
  "batchid": 2417,
  "topicid": 23935,
  "classes_total": 7,
  "classes": [
    {
      "title": "Syllogism 7",
      "id": "4430984",
      "date": "05-Sep-2024 12:12",
      "video_url": "4430984_0_3156902269938878"
    },
    {
      "title": "Syllogism 6",
      "id": "4430983",
      "date": "05-Sep-2024 12:10",
      "video_url": "4430983_0_4867344873711075"
    },
    {
      "title": "Syllogism 5",
      "id": "4430982",
      "date": "05-Sep-2024 12:08",
      "video_url": "4430982_0_9047034623918592"
    },
    {
      "title": "Syllogism 4",
      "id": "4430981",
      "date": "05-Sep-2024 12:06",
      "video_url": "4430981_0_9619377235430765"
    },
    {
      "title": "Syllogism 3",
      "id": "4430980",
      "date": "05-Sep-2024 12:04",
      "video_url": "4430980_0_8620099504191002"
    },
    {
      "title": "Syllogism 2",
      "id": "4430979",
      "date": "05-Sep-2024 12:02",
      "video_url": "4430979_0_1750079573601466"
    },
    {
      "title": "Syllogism 1",
      "id": "4430978",
      "date": "05-Sep-2024 12:00",
      "video_url": "4430978_0_5210482559539144"
    }
  ],
  "notes_total": 0,
  "notes": []
}