{
  "batchid": 3168,
  "topicid": 32442,
  "classes_total": 4,
  "classes": [
    {
      "title": "Class-05 | UP Special | UP की प्रमुख नदियाँ",
      "id": "4530487",
      "date": "26-Aug-2025 11:00",
      "video_url": "4530487_0_7003122942053929"
    },
    {
      "title": "Class-03 | UP Special",
      "id": "4528113",
      "date": "23-Aug-2025 09:00",
      "video_url": "4528113_0_1083738612223544"
    },
    {
      "title": "Class-02 | UP Special",
      "id": "4526973",
      "date": "22-Aug-2025 09:00",
      "video_url": "4526973_0_6039633368679548"
    },
    {
      "title": "Class-01 | UP Special",
      "id": "4524672",
      "date": "20-Aug-2025 09:00",
      "video_url": "4524672_0_9299486407011133"
    }
  ],
  "notes_total": 161,
  "notes": [
    {
      "id": 710397,
      "title": "Eco & Env. | 7-8 Oct | Class PNG",
      "url": "https://cwmediabkt99.crwilladmin.com/92013a99927c4842b0a70fbd6f064a95:crwilladmin/class-attachment/68e621b445291_ilovepdf_merged_18.pdf",
      "date": "03-Nov-2025"
    },
    {
      "id": 710396,
      "title": "Env & Eco | 29 Sept - 3 Oct | Class PNG",
      "url": "https://cwmediabkt99.crwilladmin.com/92013a99927c4842b0a70fbd6f064a95:crwilladmin/class-attachment/68e0ebb517ef2_ilovepdf_merged_13.pdf",
      "date": "03-Nov-2025"
    },
    {
      "id": 710395,
      "title": "Env. & Eco. | 26 Sept | Class PNG",
      "url": "https://cwmediabkt99.crwilladmin.com/92013a99927c4842b0a70fbd6f064a95:crwilladmin/class-attachment/68da46a071645_Env._Eco._Class_37.pdf",
      "date": "03-Nov-2025"
    },
    {
      "id": 710394,
      "title": "Eco and Env | 18-24 Sept | Class PNG",
      "url": "https://cwmediabkt99.crwilladmin.com/92013a99927c4842b0a70fbd6f064a95:crwilladmin/class-attachment/68d4cbf515035_ilovepdf_merged_3.pdf",
      "date": "03-Nov-2025"
    },
    {
      "id": 710393,
      "title": "Eco. & Env. | 16 Sept | Class PNG",
      "url": "https://cwmediabkt99.crwilladmin.com/92013a99927c4842b0a70fbd6f064a95:crwilladmin/class-attachment/68cbb1321349f_Env._Eco._Class_29.pdf",
      "date": "03-Nov-2025"
    },
    {
      "id": 710392,
      "title": "Eco. & Env. | 14 Sept | Class PNG",
      "url": "https://cwmediabkt99.crwilladmin.com/92013a99927c4842b0a70fbd6f064a95:crwilladmin/class-attachment/68cbb06309785_Env._Eco._Class_28.pdf",
      "date": "03-Nov-2025"
    },
    {
      "id": 710391,
      "title": "Env. & Eco. | 12 Sept | Class PNG",
      "url": "https://cwmediabkt99.crwilladmin.com/92013a99927c4842b0a70fbd6f064a95:crwilladmin/class-attachment/68c4f321d51f7_Env._Eco._Class_26.pdf",
      "date": "03-Nov-2025"
    },
    {
      "id": 710390,
      "title": "Env. & Eco. | 11 Sept | Class PNG",
      "url": "https://cwmediabkt99.crwilladmin.com/92013a99927c4842b0a70fbd6f064a95:crwilladmin/class-attachment/68c3a3eb0625e_Env._Eco._Class_25.pdf",
      "date": "03-Nov-2025"
    },
    {
      "id": 710389,
      "title": "Env. & Eco.| 9-11 Sept | Class PNG",
      "url": "https://cwmediabkt99.crwilladmin.com/92013a99927c4842b0a70fbd6f064a95:crwilladmin/class-attachment/68c2af22eb6b9_ilovepdf_merged_94_compressed.pdf",
      "date": "03-Nov-2025"
    },
    {
      "id": 710388,
      "title": "Env. & Eco. | 2 Sept | Class PNG",
      "url": "https://cwmediabkt99.crwilladmin.com/92013a99927c4842b0a70fbd6f064a95:crwilladmin/class-attachment/68b927b34ea4d_Env._Eco._Class_17.pdf",
      "date": "03-Nov-2025"
    },
    {
      "id": 710387,
      "title": "Env. & Eco. | 1 Sept | Class png",
      "url": "https://cwmediabkt99.crwilladmin.com/92013a99927c4842b0a70fbd6f064a95:crwilladmin/class-attachment/68b67e78c370e_Env._Eco._Class_16.pdf",
      "date": "03-Nov-2025"
    },
    {
      "id": 710386,
      "title": "Env. & Eco. | 30 Aug | Class PNG",
      "url": "https://cwmediabkt99.crwilladmin.com/92013a99927c4842b0a70fbd6f064a95:crwilladmin/class-attachment/68b5613cf000a_Env._Eco._Class_15.pdf",
      "date": "03-Nov-2025"
    },
    {
      "id": 710385,
      "title": "Env. & Eco | 29 Aug | Class PNG",
      "url": "https://cwmediabkt99.crwilladmin.com/92013a99927c4842b0a70fbd6f064a95:crwilladmin/class-attachment/68b291d7d0093_Env._Eco._Class_14_compressed.pdf",
      "date": "03-Nov-2025"
    },
    {
      "id": 710384,
      "title": "Env. & Eco. | 27 Aug | Class PNG",
      "url": "https://cwmediabkt99.crwilladmin.com/92013a99927c4842b0a70fbd6f064a95:crwilladmin/class-attachment/68b149e3afbfb_Env._Eco._Class_12.pdf",
      "date": "03-Nov-2025"
    },
    {
      "id": 710383,
      "title": "Env. & Eco. | 26 Aug | Class PNG-I",
      "url": "https://cwmediabkt99.crwilladmin.com/92013a99927c4842b0a70fbd6f064a95:crwilladmin/class-attachment/68ae935813113_Env._Eco._Class_11.pdf",
      "date": "03-Nov-2025"
    },
    {
      "id": 710382,
      "title": "Env. & Eco. | 25 Aug | Class PNG-I",
      "url": "https://cwmediabkt99.crwilladmin.com/92013a99927c4842b0a70fbd6f064a95:crwilladmin/class-attachment/68ad565eb05c8__.pdf",
      "date": "03-Nov-2025"
    },
    {
      "id": 710381,
      "title": "Env. & Eco. | 25 Aug | Class PNG",
      "url": "https://cwmediabkt99.crwilladmin.com/92013a99927c4842b0a70fbd6f064a95:crwilladmin/class-attachment/68ad56116cda6_Env._Eco._Class_10.pdf",
      "date": "03-Nov-2025"
    },
    {
      "id": 710380,
      "title": "Env & Eco | 23 Aug | Class PNG",
      "url": "https://cwmediabkt99.crwilladmin.com/92013a99927c4842b0a70fbd6f064a95:crwilladmin/class-attachment/68ac03783c544_Env._Eco._Class_9.pdf",
      "date": "03-Nov-2025"
    },
    {
      "id": 710379,
      "title": "Env & Eco | 22 Aug | Class PNG",
      "url": "https://cwmediabkt99.crwilladmin.com/92013a99927c4842b0a70fbd6f064a95:crwilladmin/class-attachment/68ac01f976eb7_Env._Eco._Class_8.pdf",
      "date": "03-Nov-2025"
    },
    {
      "id": 710378,
      "title": "Env. & Eco. | 21 Aug | Class PNG",
      "url": "https://cwmediabkt99.crwilladmin.com/92013a99927c4842b0a70fbd6f064a95:crwilladmin/class-attachment/68a804d95976c_Env._Eco._Class_7.pdf",
      "date": "03-Nov-2025"
    },
    {
      "id": 710377,
      "title": "Env and Eco | 20 Aug | Class PNG",
      "url": "https://cwmediabkt99.crwilladmin.com/92013a99927c4842b0a70fbd6f064a95:crwilladmin/class-attachment/68a55dabd29a9_Env._and_Eco._Class_5.pdf",
      "date": "03-Nov-2025"
    },
    {
      "id": 710376,
      "title": "Env. & Eco | 18 Aug | Class PNG",
      "url": "https://cwmediabkt99.crwilladmin.com/92013a99927c4842b0a70fbd6f064a95:crwilladmin/class-attachment/68a41256b5e08_Env._Eco._Class_4.pdf",
      "date": "03-Nov-2025"
    },
    {
      "id": 710375,
      "title": "Ecology | 14 Aug | Class PNG",
      "url": "https://cwmediabkt99.crwilladmin.com/92013a99927c4842b0a70fbd6f064a95:crwilladmin/class-attachment/689d7e7d2cfa6_Env._Eco._Class_2.pdf",
      "date": "03-Nov-2025"
    },
    {
      "id": 710374,
      "title": "Eco | 15 May | Class PNG",
      "url": "https://cwmediabkt99.crwilladmin.com/92013a99927c4842b0a70fbd6f064a95:crwilladmin/class-attachment/682581dba2409_CW15Maycompressed.pdf",
      "date": "03-Nov-2025"
    },
    {
      "id": 710373,
      "title": "Pol | 06 Oct | Class PNG",
      "url": "https://cwmediabkt99.crwilladmin.com/92013a99927c4842b0a70fbd6f064a95:crwilladmin/class-attachment/68e4d59ea6382_10071413.pdf",
      "date": "03-Nov-2025"
    },
    {
      "id": 710372,
      "title": "Pol | 20 Sept | Class PNG",
      "url": "https://cwmediabkt99.crwilladmin.com/92013a99927c4842b0a70fbd6f064a95:crwilladmin/class-attachment/68d0f09603f5c_09201003.pdf",
      "date": "03-Nov-2025"
    },
    {
      "id": 710371,
      "title": "Pol | 16,17,18 Sept | Class PNG",
      "url": "https://cwmediabkt99.crwilladmin.com/92013a99927c4842b0a70fbd6f064a95:crwilladmin/class-attachment/68ccfe721b187_09171004_merged_compressed.pdf",
      "date": "03-Nov-2025"
    },
    {
      "id": 710370,
      "title": "Pol | 9-11 Sept | Class PNG",
      "url": "https://cwmediabkt99.crwilladmin.com/92013a99927c4842b0a70fbd6f064a95:crwilladmin/class-attachment/68c2adbc6e188_09081008_merged_compressed.pdf",
      "date": "03-Nov-2025"
    },
    {
      "id": 710369,
      "title": "Pol | 14 Aug | Class PNG",
      "url": "https://cwmediabkt99.crwilladmin.com/92013a99927c4842b0a70fbd6f064a95:crwilladmin/class-attachment/689dae704db9a_08141007.pdf",
      "date": "03-Nov-2025"
    },
    {
      "id": 710368,
      "title": "Pol | 12 Aug | Class PNG",
      "url": "https://cwmediabkt99.crwilladmin.com/92013a99927c4842b0a70fbd6f064a95:crwilladmin/class-attachment/689acb376b40a_08121009.pdf",
      "date": "03-Nov-2025"
    },
    {
      "id": 710367,
      "title": "21 June 2022 Class Notes",
      "url": "https://cwmediabkt99.crwilladmin.com/92013a99927c4842b0a70fbd6f064a95:crwilladmin/class-attachment/1655827990-21_june_by_manjesh_sir_7_00AM.pdf",
      "date": "03-Nov-2025"
    },
    {
      "id": 710366,
      "title": "Constitutions of Major Countries of the World (Part-3)",
      "url": "https://cwmediabkt99.crwilladmin.com/92013a99927c4842b0a70fbd6f064a95:crwilladmin/class-attachment/1655300704-Constitutions_of_major_countries_of_the_world_(Part-3).pdf",
      "date": "03-Nov-2025"
    },
    {
      "id": 710365,
      "title": "09 June 2022 Class Notes",
      "url": "https://cwmediabkt99.crwilladmin.com/92013a99927c4842b0a70fbd6f064a95:crwilladmin/class-attachment/1654755883-9_may_manjesh_sir.pdf",
      "date": "03-Nov-2025"
    },
    {
      "id": 710364,
      "title": "08 June 2022 Class Notes",
      "url": "https://cwmediabkt99.crwilladmin.com/92013a99927c4842b0a70fbd6f064a95:crwilladmin/class-attachment/1654687974-8_Jun_by_Manjesh_sir_7_00AM.pdf",
      "date": "03-Nov-2025"
    },
    {
      "id": 710363,
      "title": "01 Jun 2022 Class Notes",
      "url": "https://cwmediabkt99.crwilladmin.com/92013a99927c4842b0a70fbd6f064a95:crwilladmin/class-attachment/1654063173-1_Jun_by_Manjesh_sir_7_00AM.pdf",
      "date": "03-Nov-2025"
    },
    {
      "id": 710362,
      "title": "31 May 2022 Class Notes",
      "url": "https://cwmediabkt99.crwilladmin.com/92013a99927c4842b0a70fbd6f064a95:crwilladmin/class-attachment/1654063173-31_may_by_manjesh_sir_7_00AM.pdf",
      "date": "03-Nov-2025"
    },
    {
      "id": 710361,
      "title": "30 May 2022 Class Notes",
      "url": "https://cwmediabkt99.crwilladmin.com/92013a99927c4842b0a70fbd6f064a95:crwilladmin/class-attachment/1653902819-30may_by_manjesh_sir_7_00AM_compressed.pdf",
      "date": "03-Nov-2025"
    },
    {
      "id": 710360,
      "title": "State Executive and Legislature",
      "url": "https://cwmediabkt99.crwilladmin.com/92013a99927c4842b0a70fbd6f064a95:crwilladmin/class-attachment/1643705836-THE_STATE_EXECUTIVE_AND_LEGISLATURE_(Hindi).pdf",
      "date": "03-Nov-2025"
    },
    {
      "id": 710359,
      "title": "Indian Federalism & Center State Relation",
      "url": "https://cwmediabkt99.crwilladmin.com/92013a99927c4842b0a70fbd6f064a95:crwilladmin/class-attachment/1643275553-Indian_Federalism_Center_State_Relation.pdf",
      "date": "03-Nov-2025"
    },
    {
      "id": 710358,
      "title": "Union of India and Center State Relations",
      "url": "https://cwmediabkt99.crwilladmin.com/92013a99927c4842b0a70fbd6f064a95:crwilladmin/class-attachment/1642493416-79807crwill.pdf",
      "date": "03-Nov-2025"
    },
    {
      "id": 710357,
      "title": "Constitution Meaning Type + Fundamental Right  + DPSP + FD",
      "url": "https://cwmediabkt99.crwilladmin.com/92013a99927c4842b0a70fbd6f064a95:crwilladmin/class-attachment/1641386195-Constitution_Meaning_Type_+_Fundamental_Right_+_DPSP_+_FD.pdf",
      "date": "03-Nov-2025"
    },
    {
      "id": 710356,
      "title": "Consitutional History of India & Premble (Volume-1)",
      "url": "https://cwmediabkt99.crwilladmin.com/92013a99927c4842b0a70fbd6f064a95:crwilladmin/class-attachment/1636621214-Consitutional_history_of_India_Premble_(Volume-1).pdf",
      "date": "03-Nov-2025"
    },
    {
      "id": 710355,
      "title": "Union and Its territories & Citizenship",
      "url": "https://cwmediabkt99.crwilladmin.com/92013a99927c4842b0a70fbd6f064a95:crwilladmin/class-attachment/1636621214-Union_and_Its_territories_Citizenship.pdf",
      "date": "03-Nov-2025"
    },
    {
      "id": 710354,
      "title": "Geo | 27 Aug | Class PNG",
      "url": "https://cwmediabkt99.crwilladmin.com/92013a99927c4842b0a70fbd6f064a95:crwilladmin/class-attachment/68b1496670bdf_Today_Topic_East_Asia1.pdf",
      "date": "03-Nov-2025"
    },
    {
      "id": 710353,
      "title": "Geo | 26 Aug | Class PNG",
      "url": "https://cwmediabkt99.crwilladmin.com/92013a99927c4842b0a70fbd6f064a95:crwilladmin/class-attachment/68b148c66dac7_East_Asia1_BPSC_2025_Foundation_Batch_UPSC_IAS_202526_Hindi01_UPSC_IAS_202526_Hindi02_UPSC_IAS_202526_Hindi03_UPSC_IAS_202526_Hindi04_Geography_Amit_Tomar_Sir.pdf",
      "date": "03-Nov-2025"
    },
    {
      "id": 710352,
      "title": "Geomorphology (Climatology) Volume-1 to 2",
      "url": "https://cwmediabkt99.crwilladmin.com/92013a99927c4842b0a70fbd6f064a95:crwilladmin/class-attachment/68ad9de44a15f_Geomorphology_Climatology_Volume_1_to_2_2.pdf",
      "date": "03-Nov-2025"
    },
    {
      "id": 710351,
      "title": "Geo | 23 Aug | Class PNG",
      "url": "https://cwmediabkt99.crwilladmin.com/92013a99927c4842b0a70fbd6f064a95:crwilladmin/class-attachment/68ac0311a36fa_CW_Lecture_97.pdf",
      "date": "03-Nov-2025"
    },
    {
      "id": 710350,
      "title": "Geo | 22 Aug | Class PNG",
      "url": "https://cwmediabkt99.crwilladmin.com/92013a99927c4842b0a70fbd6f064a95:crwilladmin/class-attachment/68a83a028bdae_CW_Lecture_96.pdf",
      "date": "03-Nov-2025"
    },
    {
      "id": 710349,
      "title": "Geo | 21 Aug | Class PNG",
      "url": "https://cwmediabkt99.crwilladmin.com/92013a99927c4842b0a70fbd6f064a95:crwilladmin/class-attachment/68a6ef7fe9f40_CW_Lecture_95.pdf",
      "date": "03-Nov-2025"
    },
    {
      "id": 710348,
      "title": "South America - Volume 1 & 2",
      "url": "https://cwmediabkt99.crwilladmin.com/92013a99927c4842b0a70fbd6f064a95:crwilladmin/class-attachment/68a6ee958d975_South_America_Volume_1_2.pdf",
      "date": "03-Nov-2025"
    },
    {
      "id": 710347,
      "title": "World North America Final",
      "url": "https://cwmediabkt99.crwilladmin.com/92013a99927c4842b0a70fbd6f064a95:crwilladmin/class-attachment/68a6ee5c7b280_World_North_America_final.pdf",
      "date": "03-Nov-2025"
    },
    {
      "id": 710346,
      "title": "Europe Volume-1& 2",
      "url": "https://cwmediabkt99.crwilladmin.com/92013a99927c4842b0a70fbd6f064a95:crwilladmin/class-attachment/68a6edf47f628_Europe_Volume_1_2.pdf",
      "date": "03-Nov-2025"
    },
    {
      "id": 710345,
      "title": "Geo | 20 Aug | Class PNG",
      "url": "https://cwmediabkt99.crwilladmin.com/92013a99927c4842b0a70fbd6f064a95:crwilladmin/class-attachment/68a5a2f1433ff_CW_Lecture_93_merged.pdf",
      "date": "03-Nov-2025"
    },
    {
      "id": 710344,
      "title": "Geo | 13 Aug | Class PNG",
      "url": "https://cwmediabkt99.crwilladmin.com/92013a99927c4842b0a70fbd6f064a95:crwilladmin/class-attachment/689d7ca2bccd4_CW_Lecture90.pdf",
      "date": "03-Nov-2025"
    },
    {
      "id": 710343,
      "title": "Geo | 05 Aug | Class PNG",
      "url": "https://cwmediabkt99.crwilladmin.com/92013a99927c4842b0a70fbd6f064a95:crwilladmin/class-attachment/689301d3708a4_CW_Lecture_85.pdf",
      "date": "03-Nov-2025"
    },
    {
      "id": 710342,
      "title": "Geo | 04 Aug | Class PNG",
      "url": "https://cwmediabkt99.crwilladmin.com/92013a99927c4842b0a70fbd6f064a95:crwilladmin/class-attachment/6890915c1bcc6_CW_Lecture_83.pdf",
      "date": "03-Nov-2025"
    },
    {
      "id": 710341,
      "title": "Geo | 01 Aug | Class PNG",
      "url": "https://educp.crwilladmin.com/uploads/class-attachment/lclsys_CW_Lecture_82.pdf",
      "date": "03-Nov-2025"
    },
    {
      "id": 710340,
      "title": "Geo | 30 July | Class PNG",
      "url": "https://educp.crwilladmin.com/uploads/class-attachment/lclsys_CW_Lecture81.pdf",
      "date": "03-Nov-2025"
    },
    {
      "id": 710339,
      "title": "Geo | 29 July | Class PNG",
      "url": "https://educp.crwilladmin.com/uploads/class-attachment/lclsys_CW_Lecture_80.pdf",
      "date": "03-Nov-2025"
    },
    {
      "id": 710338,
      "title": "Geo | 28 July | Class PNG",
      "url": "https://educp.crwilladmin.com/uploads/class-attachment/lclsys_CW_Lecture79.pdf",
      "date": "03-Nov-2025"
    },
    {
      "id": 710337,
      "title": "Geo | 24 July | Class PNG",
      "url": "https://educp.crwilladmin.com/uploads/class-attachment/lclsys_CW_Lecture78_compressed.pdf",
      "date": "03-Nov-2025"
    },
    {
      "id": 710336,
      "title": "Geo | 23 July | Class PNG",
      "url": "https://educp.crwilladmin.com/uploads/class-attachment/lclsys_CW_Lecture76_compressed.pdf",
      "date": "03-Nov-2025"
    },
    {
      "id": 710335,
      "title": "Geo | 22 July | Class PNG",
      "url": "https://cwmediabkt99.crwilladmin.com/92013a99927c4842b0a70fbd6f064a95:crwilladmin/class-attachment/6880c18b90727_CW_Lecture75compressed.pdf",
      "date": "03-Nov-2025"
    },
    {
      "id": 710334,
      "title": "Geo | 21 July | Class PNG",
      "url": "https://cwmediabkt99.crwilladmin.com/92013a99927c4842b0a70fbd6f064a95:crwilladmin/class-attachment/687e066580d9d_CW_Lecture73.pdf",
      "date": "03-Nov-2025"
    },
    {
      "id": 710333,
      "title": "Geo | 16 July | Class PNG",
      "url": "https://cwmediabkt99.crwilladmin.com/92013a99927c4842b0a70fbd6f064a95:crwilladmin/class-attachment/6878aec4ef2cb_CW_Lecture71.pdf",
      "date": "03-Nov-2025"
    },
    {
      "id": 710332,
      "title": "Geo | 14-15 July | Class PNG",
      "url": "https://cwmediabkt99.crwilladmin.com/92013a99927c4842b0a70fbd6f064a95:crwilladmin/class-attachment/6875eb8b43325_CW_Lecture68mergedcompressed.pdf",
      "date": "03-Nov-2025"
    },
    {
      "id": 710331,
      "title": "Geo | 12 July | Class PNG",
      "url": "https://cwmediabkt99.crwilladmin.com/92013a99927c4842b0a70fbd6f064a95:crwilladmin/class-attachment/6874a13537d6a_CW_Lecture67.pdf",
      "date": "03-Nov-2025"
    },
    {
      "id": 710330,
      "title": "Geo Class (61-65) Notes",
      "url": "https://cwmediabkt99.crwilladmin.com/92013a99927c4842b0a70fbd6f064a95:crwilladmin/class-attachment/686e30a38f2b9_CW_Lecture61mergedcompressed.pdf",
      "date": "03-Nov-2025"
    },
    {
      "id": 710323,
      "title": "His | 3 Nov | Class PNG",
      "url": "https://cwmediabkt99.crwilladmin.com/92013a99927c4842b0a70fbd6f064a95:crwilladmin/class-attachment/69085652abaae_shashank_Sir_10am_to12pm_modern_history_3_Nov_2025_compressed.pdf",
      "date": "03-Nov-2025"
    },
    {
      "id": 710322,
      "title": "His | 1 Nov | Class PNG",
      "url": "https://cwmediabkt99.crwilladmin.com/92013a99927c4842b0a70fbd6f064a95:crwilladmin/class-attachment/69085459e4f8e_shashank_Sir_10am_to12pm_modern_history_1_Nov_2025_1_compressed.pdf",
      "date": "03-Nov-2025"
    },
    {
      "id": 710321,
      "title": "His | 31 Oct | Class PNG",
      "url": "https://cwmediabkt99.crwilladmin.com/92013a99927c4842b0a70fbd6f064a95:crwilladmin/class-attachment/69045b738f6a3_shashank_Sir_10am_to12pm_modern_history_31_October_2025_compressed.pdf",
      "date": "03-Nov-2025"
    },
    {
      "id": 710320,
      "title": "His | 30 Oct | Class PNG",
      "url": "https://cwmediabkt99.crwilladmin.com/92013a99927c4842b0a70fbd6f064a95:crwilladmin/class-attachment/690306feda9d6_shashank_Sir_10am_to12pm_modern_history_30_October_2025.pdf",
      "date": "03-Nov-2025"
    },
    {
      "id": 710319,
      "title": "His | 29 Oct | Class PNG",
      "url": "https://cwmediabkt99.crwilladmin.com/92013a99927c4842b0a70fbd6f064a95:crwilladmin/class-attachment/6901b8226689d_shashank_Sir_10am_to12pm_modern_history_29_October_2025_compressed.pdf",
      "date": "03-Nov-2025"
    },
    {
      "id": 710318,
      "title": "His | 25,27,28 Oct | Class PNG",
      "url": "https://cwmediabkt99.crwilladmin.com/92013a99927c4842b0a70fbd6f064a95:crwilladmin/class-attachment/69007e5f1979e_ilovepdf_merged_19_compressed.pdf",
      "date": "03-Nov-2025"
    },
    {
      "id": 710317,
      "title": "His | 6,7,8 Oct | Class PNG",
      "url": "https://cwmediabkt99.crwilladmin.com/92013a99927c4842b0a70fbd6f064a95:crwilladmin/class-attachment/68e62286f318f_ilovepdf_merged_19_compressed.pdf",
      "date": "03-Nov-2025"
    },
    {
      "id": 710316,
      "title": "His | 26 Aug | Class PNG",
      "url": "https://cwmediabkt99.crwilladmin.com/92013a99927c4842b0a70fbd6f064a95:crwilladmin/class-attachment/68ad72ef8e076_Shashank_Sir_11.00_AM_26_August2025_compressed.pdf",
      "date": "03-Nov-2025"
    },
    {
      "id": 710315,
      "title": "His | 24 Aug | Class PNG",
      "url": "https://cwmediabkt99.crwilladmin.com/92013a99927c4842b0a70fbd6f064a95:crwilladmin/class-attachment/68ac047f4138c_Shashank_Sir_11_am_to_1_pm_24_August20251_compressed.pdf",
      "date": "03-Nov-2025"
    },
    {
      "id": 710314,
      "title": "His | 23 Aug | Class PNG",
      "url": "https://cwmediabkt99.crwilladmin.com/92013a99927c4842b0a70fbd6f064a95:crwilladmin/class-attachment/68ac029ad2a7c_Shashank_Sir_11_am_to_1_pm_23_August2025.pdf",
      "date": "03-Nov-2025"
    },
    {
      "id": 710313,
      "title": "His | 22 Aug | Class PNG",
      "url": "https://cwmediabkt99.crwilladmin.com/92013a99927c4842b0a70fbd6f064a95:crwilladmin/class-attachment/68ac013783aa5_Shashank_Sir_app_yt_22_Aug_330pm.pdf",
      "date": "03-Nov-2025"
    },
    {
      "id": 710312,
      "title": "His | 22 Aug | Class PNG",
      "url": "https://cwmediabkt99.crwilladmin.com/92013a99927c4842b0a70fbd6f064a95:crwilladmin/class-attachment/68a837b75f955_Shashank_Sir_11.00_AM_22_August2025.pdf",
      "date": "03-Nov-2025"
    },
    {
      "id": 710311,
      "title": "His | 21 Aug | Class PNG",
      "url": "https://cwmediabkt99.crwilladmin.com/92013a99927c4842b0a70fbd6f064a95:crwilladmin/class-attachment/68a8044d4aa93_shashank_Sir_11am_to1pm_medieval_history_21_August_2025.pdf",
      "date": "03-Nov-2025"
    },
    {
      "id": 710310,
      "title": "G.S. - Medieval History",
      "url": "https://cwmediabkt99.crwilladmin.com/92013a99927c4842b0a70fbd6f064a95:crwilladmin/class-attachment/68a6e43066016_G.S._Medieval_History_pdf.pdf",
      "date": "03-Nov-2025"
    },
    {
      "id": 710309,
      "title": "His | 20 Aug | Class PNG",
      "url": "https://cwmediabkt99.crwilladmin.com/92013a99927c4842b0a70fbd6f064a95:crwilladmin/class-attachment/68a5a24d8b587_Shashank_Sir_11.00_AM_20_August2025.pdf",
      "date": "03-Nov-2025"
    },
    {
      "id": 710308,
      "title": "His| 19 Aug | Class PNG",
      "url": "https://cwmediabkt99.crwilladmin.com/92013a99927c4842b0a70fbd6f064a95:crwilladmin/class-attachment/68a55d16a4fd7_shashank_Sir_11am_to1pm_medieval_history_19_Augus_2025.pdf",
      "date": "03-Nov-2025"
    },
    {
      "id": 710307,
      "title": "His | 18 Aug | Class PNG",
      "url": "https://cwmediabkt99.crwilladmin.com/92013a99927c4842b0a70fbd6f064a95:crwilladmin/class-attachment/68a4117f1156c_shashank_Sir_11am_to1pm_medieval_history_18_August_2025.pdf",
      "date": "03-Nov-2025"
    },
    {
      "id": 710306,
      "title": "His | 14 Aug | Class PNG",
      "url": "https://cwmediabkt99.crwilladmin.com/92013a99927c4842b0a70fbd6f064a95:crwilladmin/class-attachment/689daeff98704_shashank_Sir_11am_to1pm_medieval_history_14_August_2025.pdf",
      "date": "03-Nov-2025"
    },
    {
      "id": 710305,
      "title": "His | 13 Aug | Class PNG",
      "url": "https://cwmediabkt99.crwilladmin.com/92013a99927c4842b0a70fbd6f064a95:crwilladmin/class-attachment/689d7c5c63013_shashank_Sir_11am_to1pm_medieval_history_13_Augus_2025.pdf",
      "date": "03-Nov-2025"
    },
    {
      "id": 710304,
      "title": "His | 07 Aug | Class PNG",
      "url": "https://cwmediabkt99.crwilladmin.com/92013a99927c4842b0a70fbd6f064a95:crwilladmin/class-attachment/6894670e00f30_Shasank_Sir_11.00_AM_07Aug_compressed.pdf",
      "date": "03-Nov-2025"
    },
    {
      "id": 710303,
      "title": "His | 06 Aug | Class PNG",
      "url": "https://cwmediabkt99.crwilladmin.com/92013a99927c4842b0a70fbd6f064a95:crwilladmin/class-attachment/68944b76391c7_shashank_Sir_11am_to1pm_medieval_history_06_August_2025_compressed.pdf",
      "date": "03-Nov-2025"
    },
    {
      "id": 710302,
      "title": "His | 05 Aug | Class PNG",
      "url": "https://cwmediabkt99.crwilladmin.com/92013a99927c4842b0a70fbd6f064a95:crwilladmin/class-attachment/689301462f6bf_shashank_Sir_11am_to1pm_medieva_history_05_August_2025_compressed.pdf",
      "date": "03-Nov-2025"
    },
    {
      "id": 710301,
      "title": "His | 04 Aug | Class PNG",
      "url": "https://cwmediabkt99.crwilladmin.com/92013a99927c4842b0a70fbd6f064a95:crwilladmin/class-attachment/6890904fab612_Shashank_Sir_11.00_AM_04Aug_compressed.pdf",
      "date": "03-Nov-2025"
    },
    {
      "id": 710300,
      "title": "His | 02 Aug | Class PNG",
      "url": "https://cwmediabkt99.crwilladmin.com/92013a99927c4842b0a70fbd6f064a95:crwilladmin/class-attachment/68905a9b6f762_shashank_Sir_11am_to1pm_medieva_history_02_August_2025_compressed.pdf",
      "date": "03-Nov-2025"
    },
    {
      "id": 710299,
      "title": "His | 01 Aug | Class PNG",
      "url": "https://educp.crwilladmin.com/uploads/class-attachment/lclsys_shashank_Sir_11am_to1pm_medieva_history_01_August_2025_compressed.pdf",
      "date": "03-Nov-2025"
    },
    {
      "id": 710298,
      "title": "Modern History | 31 July | Class PNG",
      "url": "https://educp.crwilladmin.com/uploads/class-attachment/lclsys_modern_history_lecture_31st_july.pdf",
      "date": "03-Nov-2025"
    },
    {
      "id": 710297,
      "title": "His | 31 July | Class PNG",
      "url": "https://educp.crwilladmin.com/uploads/class-attachment/lclsys_shashank_Sir_11am_to1pm_medieva_history_31_july_2025_compressed.pdf",
      "date": "03-Nov-2025"
    },
    {
      "id": 710296,
      "title": "His | 30 July | Class PNG",
      "url": "https://educp.crwilladmin.com/uploads/class-attachment/lclsys_shashank_Sir_11am_to1pm_medieva_history_30_july_2025_compressed.pdf",
      "date": "03-Nov-2025"
    },
    {
      "id": 710295,
      "title": "Modern History| Lecture -05 | Class PNG",
      "url": "https://educp.crwilladmin.com/uploads/class-attachment/lclsys_lecture_5_modern_history.pdf",
      "date": "03-Nov-2025"
    },
    {
      "id": 710294,
      "title": "His | 29 July | Class PNG",
      "url": "https://educp.crwilladmin.com/uploads/class-attachment/lclsys_shashank_Sir_11am_to1pm_medieva_history_29_july_2025.pdf",
      "date": "03-Nov-2025"
    },
    {
      "id": 710293,
      "title": "Modern History| Lecture -04 | Class PNG",
      "url": "https://educp.crwilladmin.com/uploads/class-attachment/lclsys_modern_history_lecture_4.pdf",
      "date": "03-Nov-2025"
    },
    {
      "id": 710292,
      "title": "His | 28 July | Class PNG",
      "url": "https://educp.crwilladmin.com/uploads/class-attachment/lclsys_shashank_Sir_11am_to1pm_medieva_history_28_july_2025.pdf",
      "date": "03-Nov-2025"
    },
    {
      "id": 710291,
      "title": "Modern History| Lecture -03 | Class PNG",
      "url": "https://educp.crwilladmin.com/uploads/class-attachment/lclsys_lecture_3_modern_history_compressed.pdf",
      "date": "03-Nov-2025"
    },
    {
      "id": 710290,
      "title": "Modern History|  Lecture -02 | Class PNG",
      "url": "https://educp.crwilladmin.com/uploads/class-attachment/lclsys_lecture_2_Age_of_discovery.pdf",
      "date": "03-Nov-2025"
    },
    {
      "id": 710289,
      "title": "Modern History|  Lecture -01 | Class PNG",
      "url": "https://educp.crwilladmin.com/uploads/class-attachment/lclsys_MODERN_HISTORY_intro.pdf",
      "date": "03-Nov-2025"
    },
    {
      "id": 710288,
      "title": "His | 26 July | Class PNG",
      "url": "https://educp.crwilladmin.com/uploads/class-attachment/lclsys_Shashank_Sir_Medieval_26_July.pdf",
      "date": "03-Nov-2025"
    },
    {
      "id": 710287,
      "title": "His | 25 July | Class PNG",
      "url": "https://educp.crwilladmin.com/uploads/class-attachment/lclsys_Shashank_Sir_Medieval_25_July.pdf",
      "date": "03-Nov-2025"
    },
    {
      "id": 710286,
      "title": "His | 24 July | Class PNG",
      "url": "https://educp.crwilladmin.com/uploads/class-attachment/lclsys_Shashank_Sir_Medieval_24_july_1.pdf",
      "date": "03-Nov-2025"
    },
    {
      "id": 710285,
      "title": "His | 23 July | Class PNG",
      "url": "https://cwmediabkt99.crwilladmin.com/92013a99927c4842b0a70fbd6f064a95:crwilladmin/class-attachment/6880b3f73de75_Shashank_Sir_Medieval_23_julycompressed.pdf",
      "date": "03-Nov-2025"
    },
    {
      "id": 710284,
      "title": "His | 22 July | Class PNG",
      "url": "https://cwmediabkt99.crwilladmin.com/92013a99927c4842b0a70fbd6f064a95:crwilladmin/class-attachment/687f3cda13b61_Shashank_Sir_Medieval_History_22_July_25compressed.pdf",
      "date": "03-Nov-2025"
    },
    {
      "id": 710283,
      "title": "His | 21 July | Class PNG",
      "url": "https://cwmediabkt99.crwilladmin.com/92013a99927c4842b0a70fbd6f064a95:crwilladmin/class-attachment/687e05b23101b_Shashank_Sir_Medieval_21_Julycompressed.pdf",
      "date": "03-Nov-2025"
    },
    {
      "id": 710282,
      "title": "His | 19 July | Class PNG",
      "url": "https://cwmediabkt99.crwilladmin.com/92013a99927c4842b0a70fbd6f064a95:crwilladmin/class-attachment/687b411ccbefb_Probability_Class_5compressed.pdf",
      "date": "03-Nov-2025"
    },
    {
      "id": 710281,
      "title": "His | 18 July | Class PNG",
      "url": "https://cwmediabkt99.crwilladmin.com/92013a99927c4842b0a70fbd6f064a95:crwilladmin/class-attachment/6879e76a66153_Shashank_Sir_10.00_AM_18_Julycompressed.pdf",
      "date": "03-Nov-2025"
    },
    {
      "id": 710280,
      "title": "His | 16 July | Class PNG",
      "url": "https://cwmediabkt99.crwilladmin.com/92013a99927c4842b0a70fbd6f064a95:crwilladmin/class-attachment/687748b85d099_Shashank_Sir_10.00_AM_16_Julycompressed.pdf",
      "date": "03-Nov-2025"
    },
    {
      "id": 710279,
      "title": "His | 15 July | Class PNG",
      "url": "https://cwmediabkt99.crwilladmin.com/92013a99927c4842b0a70fbd6f064a95:crwilladmin/class-attachment/6875f853c27e1_Shashank_Sir_10.00_AM_15_Julycompressed.pdf",
      "date": "03-Nov-2025"
    },
    {
      "id": 710278,
      "title": "His | 14 July | Class PNG",
      "url": "https://cwmediabkt99.crwilladmin.com/92013a99927c4842b0a70fbd6f064a95:crwilladmin/class-attachment/6874aa67081eb_Shasank_Sir_10.00_AM_14Julycompressed.pdf",
      "date": "03-Nov-2025"
    },
    {
      "id": 710277,
      "title": "His | 12 July | Class PNG",
      "url": "https://cwmediabkt99.crwilladmin.com/92013a99927c4842b0a70fbd6f064a95:crwilladmin/class-attachment/687243ff23e1a_Shashank_Sir_10.00_AM_12_Julycompressed.pdf",
      "date": "03-Nov-2025"
    },
    {
      "id": 710276,
      "title": "His | 11 July | Class PNG",
      "url": "https://cwmediabkt99.crwilladmin.com/92013a99927c4842b0a70fbd6f064a95:crwilladmin/class-attachment/6870e3a5a9338_Shashank_Sir_10.00_AM_11_Julycompressed.pdf",
      "date": "03-Nov-2025"
    },
    {
      "id": 710275,
      "title": "His | 10 July | Class PNG",
      "url": "https://cwmediabkt99.crwilladmin.com/92013a99927c4842b0a70fbd6f064a95:crwilladmin/class-attachment/686f5fc3681fe_Shashank_Sir_10.00_AM_10_Julycompressed.pdf",
      "date": "03-Nov-2025"
    },
    {
      "id": 710274,
      "title": "His | 9 July | Class PNG",
      "url": "https://cwmediabkt99.crwilladmin.com/92013a99927c4842b0a70fbd6f064a95:crwilladmin/class-attachment/686e0746bb6e7_Shashank_Sir_10.00_AM_09_Julycompressed.pdf",
      "date": "03-Nov-2025"
    },
    {
      "id": 710273,
      "title": "His | 05 July | Class PNG",
      "url": "https://cwmediabkt99.crwilladmin.com/92013a99927c4842b0a70fbd6f064a95:crwilladmin/class-attachment/6868c7fd1a23a_shashank_sirhistory5thjuly_1000amcompressed.pdf",
      "date": "03-Nov-2025"
    },
    {
      "id": 710272,
      "title": "His | 2 July | Class PNG",
      "url": "https://cwmediabkt99.crwilladmin.com/92013a99927c4842b0a70fbd6f064a95:crwilladmin/class-attachment/6864d2bf7f389_Shashank_Sir_10.00_AM_2_julycompressed.pdf",
      "date": "03-Nov-2025"
    },
    {
      "id": 710271,
      "title": "His | 30 June | Class PNG",
      "url": "https://cwmediabkt99.crwilladmin.com/92013a99927c4842b0a70fbd6f064a95:crwilladmin/class-attachment/6864d2639a289_Shasank_Sir_30_june_10am_1compressed.pdf",
      "date": "03-Nov-2025"
    },
    {
      "id": 680222,
      "title": "Bpsc and Uppsc (Polity Set -1) - 150",
      "url": "https://cwmediabkt99.crwilladmin.com/92013a99927c4842b0a70fbd6f064a95:crwilladmin/class-attachment/68d25b133e0f3_Bpsc_and_Uppsc_Polity_set_1_Student_copy_150.pdf",
      "date": "23-Sep-2025"
    },
    {
      "id": 680221,
      "title": "Ancient History Sol. (BPSC And UPPSC)- (Bilingual)",
      "url": "https://cwmediabkt99.crwilladmin.com/92013a99927c4842b0a70fbd6f064a95:crwilladmin/class-attachment/68d25ad3c1ba4_Ancient_History_St._copySol._BPSC_And_UPPSC_Bilingual.pdf",
      "date": "23-Sep-2025"
    },
    {
      "id": 680220,
      "title": "Medieval History Sol. (Bilingual)",
      "url": "https://cwmediabkt99.crwilladmin.com/92013a99927c4842b0a70fbd6f064a95:crwilladmin/class-attachment/68d25abb1f081_Medieval_History_Student_copySol._Bilingual.pdf",
      "date": "23-Sep-2025"
    },
    {
      "id": 680219,
      "title": "Economics With Solution",
      "url": "https://cwmediabkt99.crwilladmin.com/92013a99927c4842b0a70fbd6f064a95:crwilladmin/class-attachment/68d25aa0b0947_Economics_s_With_Solution.pdf",
      "date": "23-Sep-2025"
    },
    {
      "id": 680218,
      "title": "Art and Culture  With Solution",
      "url": "https://cwmediabkt99.crwilladmin.com/92013a99927c4842b0a70fbd6f064a95:crwilladmin/class-attachment/68d25a84173d7_Art_and_Culture_s_With_Solution.pdf",
      "date": "23-Sep-2025"
    },
    {
      "id": 661131,
      "title": "Medieval History (Set 1 to 3)",
      "url": "https://cwmediabkt99.crwilladmin.com/92013a99927c4842b0a70fbd6f064a95:crwilladmin/class-attachment/68c2a7b4e595e_Medieval_History_Student_copySol._Set_1_to_3.pdf",
      "date": "11-Sep-2025"
    },
    {
      "id": 661130,
      "title": "SET 1 - Economics Final",
      "url": "https://cwmediabkt99.crwilladmin.com/92013a99927c4842b0a70fbd6f064a95:crwilladmin/class-attachment/68c2a79ce2f94_SET_1_ECONOMICS_FINAL.pdf",
      "date": "11-Sep-2025"
    },
    {
      "id": 639699,
      "title": "His | 25 Aug | Class PNG",
      "url": "https://cwmediabkt99.crwilladmin.com/92013a99927c4842b0a70fbd6f064a95:crwilladmin/class-attachment/68ad5f637fcc5_Sashank_Sir_330_PM_25_Aug_compressed.pdf",
      "date": "26-Aug-2025"
    },
    {
      "id": 639300,
      "title": "Ancient History Notes",
      "url": "https://cwmediabkt99.crwilladmin.com/92013a99927c4842b0a70fbd6f064a95:crwilladmin/class-attachment/68ac1e3b266ff_Ancient_History_Student_copy_100_BPSC_And_UPPSC.pdf",
      "date": "25-Aug-2025"
    },
    {
      "id": 639267,
      "title": "UP Spl. | 25 Aug | Class PNG",
      "url": "https://cwmediabkt99.crwilladmin.com/92013a99927c4842b0a70fbd6f064a95:crwilladmin/class-attachment/68ac0eca77f76_20250825094908634_1_compressed.pdf",
      "date": "25-Aug-2025"
    },
    {
      "id": 710328,
      "title": "Geo Class (1-58) Notes Part-3",
      "url": "https://cwmediabkt99.crwilladmin.com/92013a99927c4842b0a70fbd6f064a95:crwilladmin/class-attachment/686e2ffe983aa_CW_Lecture1_Final_Done_PART03.pdf",
      "date": "03-Nov-2025"
    },
    {
      "id": 710269,
      "title": "His | 26 June | Class PNG",
      "url": "https://cwmediabkt99.crwilladmin.com/92013a99927c4842b0a70fbd6f064a95:crwilladmin/class-attachment/685ceb5624dd4_Shashank_Sir_10.00_AM_26Junecompressedremoved.pdf",
      "date": "03-Nov-2025"
    },
    {
      "id": 710329,
      "title": "Geo Class (1-58) Notes Part-2",
      "url": "https://cwmediabkt99.crwilladmin.com/92013a99927c4842b0a70fbd6f064a95:crwilladmin/class-attachment/686e303392da4_CW_Lecture1_Final_Done_PART02.pdf",
      "date": "03-Nov-2025"
    },
    {
      "id": 710270,
      "title": "His | 28 June | Class PNG",
      "url": "https://cwmediabkt99.crwilladmin.com/92013a99927c4842b0a70fbd6f064a95:crwilladmin/class-attachment/686239c4923c2_Shashank_Sir_10.00_AM_28_junecompressed.pdf",
      "date": "03-Nov-2025"
    },
    {
      "id": 710327,
      "title": "Geo Class (1-58) Notes Part-1",
      "url": "https://cwmediabkt99.crwilladmin.com/92013a99927c4842b0a70fbd6f064a95:crwilladmin/class-attachment/686e2fc916310_CW_Lecture1_Final_Done_PART01.pdf",
      "date": "03-Nov-2025"
    },
    {
      "id": 710268,
      "title": "His | 25 June | Class PNG",
      "url": "https://cwmediabkt99.crwilladmin.com/92013a99927c4842b0a70fbd6f064a95:crwilladmin/class-attachment/685b9dc1a3b6f_Shashank_Sir_10.00_AM_25Junecompressed.pdf",
      "date": "03-Nov-2025"
    },
    {
      "id": 710326,
      "title": "Geo | 9 July | Class PNG",
      "url": "https://cwmediabkt99.crwilladmin.com/92013a99927c4842b0a70fbd6f064a95:crwilladmin/class-attachment/686e053778a89_CW_Lecture66.pdf",
      "date": "03-Nov-2025"
    },
    {
      "id": 710267,
      "title": "His | 24 June | Class PNG",
      "url": "https://cwmediabkt99.crwilladmin.com/92013a99927c4842b0a70fbd6f064a95:crwilladmin/class-attachment/685a6d86d314c_Shashank_Sir_10.00_AM_24Junecompressed.pdf",
      "date": "03-Nov-2025"
    },
    {
      "id": 710325,
      "title": "Geography (Geomorphology) Valume 1 to 4",
      "url": "https://cwmediabkt99.crwilladmin.com/92013a99927c4842b0a70fbd6f064a95:crwilladmin/class-attachment/684c0f4851af2_Physical_Geography_Geomorphology_1_to_4_Volumecompressed.pdf",
      "date": "03-Nov-2025"
    },
    {
      "id": 710266,
      "title": "His | 23 June | Class PNG",
      "url": "https://cwmediabkt99.crwilladmin.com/92013a99927c4842b0a70fbd6f064a95:crwilladmin/class-attachment/6858f87567907_Shashank_Sir_10.00_AM_23Junecompressed.pdf",
      "date": "03-Nov-2025"
    },
    {
      "id": 710324,
      "title": "Geography (Oceanograaphy) Valume 1 to 3",
      "url": "https://cwmediabkt99.crwilladmin.com/92013a99927c4842b0a70fbd6f064a95:crwilladmin/class-attachment/682af919413dc_Geography_Oceanograaphy_Valume_1_to_3.pdf",
      "date": "03-Nov-2025"
    },
    {
      "id": 710265,
      "title": "His | 21 June | Class PNG",
      "url": "https://cwmediabkt99.crwilladmin.com/92013a99927c4842b0a70fbd6f064a95:crwilladmin/class-attachment/6856a84684610_Shashank_Sir_10.00_AM_21Junecompressed.pdf",
      "date": "03-Nov-2025"
    },
    {
      "id": 710264,
      "title": "His | 20 June | Class PNG",
      "url": "https://cwmediabkt99.crwilladmin.com/92013a99927c4842b0a70fbd6f064a95:crwilladmin/class-attachment/685521e994023_Shashank_Sir_10.00_AM_20Junecompressed.pdf",
      "date": "03-Nov-2025"
    },
    {
      "id": 710263,
      "title": "His | 18 June | Class PNG",
      "url": "https://cwmediabkt99.crwilladmin.com/92013a99927c4842b0a70fbd6f064a95:crwilladmin/class-attachment/685264bc6d779_Shashank_Sir_10.00_AM_19Junecompressed.pdf",
      "date": "03-Nov-2025"
    },
    {
      "id": 710262,
      "title": "His | 16 June | Class PNG",
      "url": "https://cwmediabkt99.crwilladmin.com/92013a99927c4842b0a70fbd6f064a95:crwilladmin/class-attachment/684fbcff7cf22_Shashank_Sir_10.00_AM_15Junecompressed.pdf",
      "date": "03-Nov-2025"
    },
    {
      "id": 710261,
      "title": "His | 13 June | Class PNG",
      "url": "https://cwmediabkt99.crwilladmin.com/92013a99927c4842b0a70fbd6f064a95:crwilladmin/class-attachment/684bef920a956_Shashank_Sir_10.00_AM_13June.pdf",
      "date": "03-Nov-2025"
    },
    {
      "id": 710260,
      "title": "His | 6 June | Class PNG",
      "url": "https://cwmediabkt99.crwilladmin.com/92013a99927c4842b0a70fbd6f064a95:crwilladmin/class-attachment/6842acfb7457d_Shashank_Sir_10.00_AM_06Junecompressed.pdf",
      "date": "03-Nov-2025"
    },
    {
      "id": 710259,
      "title": "His | 5 June | Class PNG",
      "url": "https://cwmediabkt99.crwilladmin.com/92013a99927c4842b0a70fbd6f064a95:crwilladmin/class-attachment/6841473cc5b92_Shashank_Sir_10.00_AM_05Junecompressed.pdf",
      "date": "03-Nov-2025"
    },
    {
      "id": 710258,
      "title": "His | 4 June | Class PNG",
      "url": "https://cwmediabkt99.crwilladmin.com/92013a99927c4842b0a70fbd6f064a95:crwilladmin/class-attachment/683feaaa5466e_Shashank_Sir_10.00_AM_04June.pdf",
      "date": "03-Nov-2025"
    },
    {
      "id": 710257,
      "title": "His | 3 June | Class PNG",
      "url": "https://cwmediabkt99.crwilladmin.com/92013a99927c4842b0a70fbd6f064a95:crwilladmin/class-attachment/683ecccd207a7_Shashank_Sir_10.00_AM_03Junecompressed.pdf",
      "date": "03-Nov-2025"
    },
    {
      "id": 710256,
      "title": "His | 2 June | Class PNG",
      "url": "https://cwmediabkt99.crwilladmin.com/92013a99927c4842b0a70fbd6f064a95:crwilladmin/class-attachment/683e8435b4345_las.pdf",
      "date": "03-Nov-2025"
    },
    {
      "id": 710255,
      "title": "His | 31 May | Class PNG",
      "url": "https://cwmediabkt99.crwilladmin.com/92013a99927c4842b0a70fbd6f064a95:crwilladmin/class-attachment/683aae7f3529b_Shashank_Sir_10.00_AM_31Maycompressed.pdf",
      "date": "03-Nov-2025"
    },
    {
      "id": 710254,
      "title": "His | 28 May | Class PNG",
      "url": "https://cwmediabkt99.crwilladmin.com/92013a99927c4842b0a70fbd6f064a95:crwilladmin/class-attachment/6837fe79e7a50_Shashank_Sir_10.00_AM_28Maycompressed.pdf",
      "date": "03-Nov-2025"
    },
    {
      "id": 710253,
      "title": "His | 27 May | Class PNG",
      "url": "https://cwmediabkt99.crwilladmin.com/92013a99927c4842b0a70fbd6f064a95:crwilladmin/class-attachment/683579633c60a_Shashank_Sir_10.00_AM_27Maycompressed.pdf",
      "date": "03-Nov-2025"
    },
    {
      "id": 710252,
      "title": "His | 26 May | Class PNG",
      "url": "https://cwmediabkt99.crwilladmin.com/92013a99927c4842b0a70fbd6f064a95:crwilladmin/class-attachment/683417b2d2d61_Shashank_Sir_10.00_AM_26Maycompressed.pdf",
      "date": "03-Nov-2025"
    },
    {
      "id": 710251,
      "title": "His | 24 May | Class PNG",
      "url": "https://cwmediabkt99.crwilladmin.com/92013a99927c4842b0a70fbd6f064a95:crwilladmin/class-attachment/6833f7f05c30c_Shashank_Sir_10.00_AM_24Maycompressed.pdf",
      "date": "03-Nov-2025"
    },
    {
      "id": 710250,
      "title": "His | 22 May | Class PNG",
      "url": "https://cwmediabkt99.crwilladmin.com/92013a99927c4842b0a70fbd6f064a95:crwilladmin/class-attachment/682ee420c6da2_Shashank_Sir_10.00_AM_22Maycompressed.pdf",
      "date": "03-Nov-2025"
    },
    {
      "id": 710249,
      "title": "His | 20 May | Class PNG",
      "url": "https://cwmediabkt99.crwilladmin.com/92013a99927c4842b0a70fbd6f064a95:crwilladmin/class-attachment/682d66b08d69a_Shashank_Sir_10.00_AM_20Maycompressed.pdf",
      "date": "03-Nov-2025"
    },
    {
      "id": 710248,
      "title": "His | 17 May | Class PNG",
      "url": "https://cwmediabkt99.crwilladmin.com/92013a99927c4842b0a70fbd6f064a95:crwilladmin/class-attachment/682abe3dacc45_upsc_10.AM_1.pdf",
      "date": "03-Nov-2025"
    },
    {
      "id": 710247,
      "title": "His | 16 May | Class PNG",
      "url": "https://cwmediabkt99.crwilladmin.com/92013a99927c4842b0a70fbd6f064a95:crwilladmin/class-attachment/6828388d9430a_upsc_10.AM.pdf",
      "date": "03-Nov-2025"
    }
  ]
}